mdundo/__init__.py
mdundo/artist.py
mdundo/charts.py
mdundo/genre.py
tests/__init__.py
tests/test_artist.py
tests/test_charts.py
tests/test_genre.py
mdundo_scraper-0.0.5.dist-info/METADATA
mdundo_scraper-0.0.5.dist-info/WHEEL
mdundo_scraper-0.0.5.dist-info/top_level.txt
mdundo_scraper-0.0.5.dist-info/RECORD
