Metadata-Version: 2.1
Name: mdundo-scraper
Version: 0.0.5
Summary: Get songs data in json format from mdundo.com site with ease inspired by https://soundcloud-scraper.js.org/ 
Home-page: https://github.com/Gidraf/mdundo-scraper
Author: Gidraf Orenja
Author-email: orenjagidraf@gmail.com
Maintainer: Gidraf Orenjaa
Maintainer-email: orenjagidraf@gmail.com
License: BSD-2
Project-URL: Funding, https://donate.pypi.org
Project-URL: Source, https://github.com/Gidraf/mdundo-scraper
Project-URL: Tracker, https://github.com/Gidraf/mdundo-scraper/issues
Platform: UNKNOWN
Classifier: Development Status :: 5 - Production/Stable
Classifier: Programming Language :: Python :: 3.6
Classifier: Programming Language :: Python :: 3.7
Classifier: Programming Language :: Python :: 3.8
Classifier: Programming Language :: Python :: 3.9
Classifier: Topic :: Software Development :: Libraries :: Python Modules
Classifier: Operating System :: OS Independent
Requires-Python: >=3.6
Requires-Dist: beautifulsoup4
Requires-Dist: requests-cache
Requires-Dist: lxml
